qprint/__init__.py
qprint/qprint.py
qprint-0.0.1.dist-info/LICENSE
qprint-0.0.1.dist-info/METADATA
qprint-0.0.1.dist-info/WHEEL
qprint-0.0.1.dist-info/top_level.txt
qprint-0.0.1.dist-info/RECORD
