Metadata-Version: 2.1
Name: qprint
Version: 0.0.1
Summary: python simple function to print text or exceptions in terminal with color
Author: randomseed42
Author-email: randomseed42@protonmail.com
License: MIT
Classifier: Programming Language :: Python :: 3
Classifier: Operating System :: OS Independent
License-File: LICENSE
